ApacheTomcatManager.py
robotframework_apachetomcat-2.0.0.dist-info/LICENSE
robotframework_apachetomcat-2.0.0.dist-info/METADATA
robotframework_apachetomcat-2.0.0.dist-info/WHEEL
robotframework_apachetomcat-2.0.0.dist-info/top_level.txt
robotframework_apachetomcat-2.0.0.dist-info/RECORD
