Metadata-Version: 2.1
Name: robotframework-apachetomcat
Version: 2.0.0
Summary: A Robot Framework Apache Tomcat Manager Library
Home-page: https://github.com/peterservice-rnd/robotframework-apachetomcat
Author: JSC PETER-SERVICE
Author-email: drse_aist_all@billing.ru
License: Apache License, Version 2.0
Keywords: testing robotframework apache tomcat
Platform: UNKNOWN
Classifier: Development Status :: 5 - Production/Stable
Classifier: Intended Audience :: Developers
Classifier: Topic :: Software Development :: Testing
Classifier: License :: OSI Approved :: Apache Software License
Classifier: Programming Language :: Python :: 3.5
Classifier: Programming Language :: Python :: 3.6
Classifier: Framework :: Robot Framework :: Library
Requires-Dist: requests (==2.21.0)
Requires-Dist: robotframework (==3.0.2)
